Workbook

Sheet はじめに
A1: 同棲 → 結婚 → 結婚式 → 妊活 → 出産 → 子1歳 の計画表
A2: 作成日：2026-08-11 ／ 制度情報は2026年8月時点
A4: ■ 最初にここだけ入力してください
A5: 基準日（＝計画の起点。同棲を始める月の1日を入れる） | C5: 46296
A6: → この日付を変えると、①②の「予定開始／予定完了／目安時期」とガントが全部動きます
A8: ■ シートの構成
A9: ①ロードマップ | C9: 13フェーズの全体像。期間・費用・意思決定・リスクを1行にまとめ、右側に49ヶ月分のガントチャート
A10: ②WBS | C10: ①を分解した実行タスク一覧。濃い行＝タスク、薄い行＝その中の実行ステップ。「論点・決めること」「選択肢・候補」「判断軸・注意点」の3列が実際に迷う場所
A11: ③リスク管理表 | C11: 各フェーズで配偶者との関係が悪化する想定リスクと、早期サイン・相手側から見えている景色・予防策・初動・再発防止
A13: ■ 使い方のコツ
A14: ②WBS は行がグループ化してあります。シート左の「−」を押すと実行ステップが折りたたまれ、タスクだけの一覧になります。
A15: ②WBS の2行目でフィルタをかけられます。「フェーズ」で今の時期だけ、「区分＝法定」で期限のあるものだけ、「担当」で自分の分だけ、という見方ができます。
A16: ③リスク管理表は、確率と影響を自分たちの実感に合わせて1〜5で書き換えてください。スコアと優先度が自動で変わります。
A17: 毎週15分のミーティングで、②の「進行中」の行と③の「早期サイン」列だけを2人で見る、という使い方を想定しています。
A19: ■ 色と表記の意味
A20: 黄色のセル | C20: 自分たちで書き換える入力欄（基準日・期間・費用・確率・影響・状態・メモ）
A21: 白いセル | C21: そのまま使う内容、または自動計算（数式が入っているので上書きしない）
A22: 赤い文字・赤い背景 | C22: 法定期限があるもの／リスクの優先度が高いもの
A23: 担当欄の「妊娠する側」 | C23: 妊娠・出産する本人。「パートナー」はもう一方。あくまで一般的な例なので、実際の家庭に合わせて書き換えてください
A24: Lv列 | C24: 2＝タスク（意思決定を含む親）、3＝その中の実行ステップ
A26: ■ 記入例（②WBS の使い方）
A27: WBS-ID | B27: タスク | C27: 状態 | D27: メモ
A28: P1-02-03 | B28: 内定最低指数を調べる | C28: 進行中 | D28: 9/20に◯◯区と△△市を比較。10/5までに結論
A30: ■ 進捗サマリー（自動集計）
B31: 全件 | C31: 未着手 | D31: 進行中 | E31: 完了 | F31: 対象外 | G31: 進捗率
A32: ②WBS | B32: =COUNTA('②WBS'!$Q$3:$Q$664) | C32: =COUNTIF('②WBS'!$Q$3:$Q$664,"未着手") | D32: =COUNTIF('②WBS'!$Q$3:$Q$664,"進行中") | E32: =COUNTIF('②WBS'!$Q$3:$Q$664,"完了") | F32: =COUNTIF('②WBS'!$Q$3:$Q$664,"対象外") | G32: =IF(B32-F32=0,0,E32/(B32-F32))
A33: ③リスク管理表 | B33: =COUNTA('③リスク管理表'!$Q$3:$Q$133) | C33: =COUNTIF('③リスク管理表'!$Q$3:$Q$133,"未着手") | D33: =COUNTIF('③リスク管理表'!$Q$3:$Q$133,"進行中") | E33: =COUNTIF('③リスク管理表'!$Q$3:$Q$133,"完了") | F33: =COUNTIF('③リスク管理表'!$Q$3:$Q$133,"対象外") | G33: =IF(B33-F33=0,0,E33/(B33-F33))
A35: ■ 前提と注意
A36: ・フェーズの期間はあくまで標準モデル。特に妊活（P8）は個人差が大きく、数ヶ月〜数年の幅がある。①の黄色いセルを実態に合わせて書き換えて使う。
A37: ・妊活・妊娠の時期を後ろにずらすと、その後のフェーズも全部後ろにずれる。年齢と妊娠率の関係があるため、結婚式と妊活の順番は意識的に決める。
A38: ・費用は目安であり、地域・式場・産院・治療内容で大きく変わる。ご祝儀・親の援助・出産育児一時金50万円・児童手当・育児休業給付金は差し引く前の金額。
A39: ・制度は2026年8月時点。RSV母子免疫ワクチンの定期接種化（2026年4月〜）、こども誰でも通園制度（2026年4月〜）、出生後休業支援給付金、育児時短就業給付を反映。出産費用の保険適用化は2027〜2028年度の見込みのため、出産育児一時金50万円を前提にしている。
A40: ・助成の金額・回数・申請時期は自治体差が非常に大きい。必ず住んでいる市区町村の公式情報で確認すること。
A41: ・本表は計画テンプレートであり、医療上の助言ではない。健康・治療・接種の判断は主治医に、制度の適用可否は自治体・健保・勤務先・ハローワークに確認すること。
A42: ・商品・サービス名は2026年8月時点で一般に流通している選択肢の例であり、特定の推奨ではない。価格と仕様は必ず最新の情報を確認すること。
A43: ・③リスク管理表の確率・影響の初期値は一般的な想定値。2人の実感に合わせて必ず書き換えること。

Sheet ①ロードマップ
A1: ① ロードマップ｜同棲 → 結婚 → 結婚式 → 妊活 → 出産 → 子1歳 | E1: 黄色のセルを書き換えると、日付とガントが自動で動きます
N2: 経過月 → | O2: 0 | P2: 1 | Q2: 2 | R2: 3 | S2: 4 | T2: 5 | U2: 6 | V2: 7 | W2: 8 | X2: 9 | Y2: 10 | Z2: 11 | AA2: 12 | AB2: 13 | AC2: 14 | AD2: 15 | AE2: 16 | AF2: 17 | AG2: 18 | AH2: 19 | AI2: 20 | AJ2: 21 | AK2: 22 | AL2: 23 | AM2: 24 | AN2: 25 | AO2: 26 | AP2: 27 | AQ2: 28 | AR2: 29 | AS2: 30 | AT2: 31 | AU2: 32 | AV2: 33 | AW2: 34 | AX2: 35 | AY2: 36 | AZ2: 37 | BA2: 38 | BB2: 39 | BC2: 40 | BD2: 41 | BE2: 42 | BF2: 43 | BG2: 44 | BH2: 45 | BI2: 46 | BJ2: 47 | BK2: 48
A3: ID | B3: フェーズ | C3: このフェーズのゴール（完了条件） | D3: 期間 (月) | E3: 開始 (経過月) | F3: 終了 (経過月) | G3: 予定開始 | H3: 予定完了 | I3: 主要マイルストーン | J3: このフェーズで決めること（意思決定） | K3: 費用下限 (万円) | L3: 費用上限 (万円) | M3: 想定される最大リスク | N3: 状態 | O3: =EDATE('はじめに'!$C$5,O2) | P3: =EDATE('はじめに'!$C$5,P2) | Q3: =EDATE('はじめに'!$C$5,Q2) | R3: =EDATE('はじめに'!$C$5,R2) | S3: =EDATE('はじめに'!$C$5,S2) | T3: =EDATE('はじめに'!$C$5,T2) | U3: =EDATE('はじめに'!$C$5,U2) | V3: =EDATE('はじめに'!$C$5,V2) | ... BK3: =EDATE('はじめに'!$C$5,BK2)
A4: P1 | B4: 同棲の準備 | C4: 2人が同じ家に住み、生活費と家事のルールが決まっている状態 | D4: 3 | E4: 0 | F4: =E4+D4-1 | G4: =EDATE('はじめに'!$C$5,E4) | H4: =EDATE('はじめに'!$C$5,F4) | I4: 物件契約／引越し／住民票異動／家事分担表の完成 | J4: どのエリアに住むか（将来の保活を見越すか）／生活費の分担方式／同棲の期限（いつまでに結婚するか） | K4: 40 | L4: 90 | M4: エリア選定を「今の通勤」だけで決めて、出産後に住み替えが必要になる | N4: 未着手
A5: P2 | B5: 同棲生活の基盤づくり | C5: 家事・お金・話し合いの型ができ、貯蓄が回り始めている状態 | D5: 6 | E5: 3 | F5: =E5+D5-1 | G5: =EDATE('はじめに'!$C$5,E5) | H5: =EDATE('はじめに'!$C$5,F5) | I5: 家計の可視化／貯蓄目標の設定／週次ミーティングの定着 | J5: 共通口座に毎月いくら入れるか／各自の自由に使える額／家事の分担比率 | K5: 0 | L5: 10 | M5: 家事分担の不公平感が言語化されないまま蓄積する | N5: 未着手
A6: P3 | B6: 結婚の意思決定・両家 | C6: 両家の合意が取れ、入籍日と式の方針が決まっている状態 | D6: 3 | E6: 9 | F6: =E6+D6-1 | G6: =EDATE('はじめに'!$C$5,E6) | H6: =EDATE('はじめに'!$C$5,F6) | I6: プロポーズ／両家挨拶／顔合わせ or 結納 | J6: 結婚式をやるか（挙式のみ／披露宴／家族婚／フォトのみ／ナシ婚）／姓をどちらにするか／婚約指輪の要否と予算 | K6: 20 | L6: 120 | M6: 式の規模と費用、両家の慣習の違いで対立する | N6: 未着手
A7: P4 | B7: 入籍・行政手続き | C7: 婚姻届が受理され、全ての名義変更が完了した状態 | D7: 2 | E7: 12 | F7: =E7+D7-1 | G7: =EDATE('はじめに'!$C$5,E7) | H7: =EDATE('はじめに'!$C$5,F7) | I7: 婚姻届提出／各種名義変更の完了 | J7: 入籍日／世帯の持ち方／保険の受取人／旧姓の通称使用をするか | K7: 3 | L7: 10 | M7: 改姓した側に名義変更の実務が全部乗る | N7: 未着手
A8: P5 | B8: 結婚式の準備 | C8: 会場・衣装・招待客・演出が確定し、支払い計画がある状態 | D8: 9 | E8: 12 | F8: =E8+D8-1 | G8: =EDATE('はじめに'!$C$5,E8) | H8: =EDATE('はじめに'!$C$5,F8) | I8: 会場成約／招待状発送／最終打ち合わせ | J8: 会場（持ち込み料・見積の増減）／招待客リスト／衣装は提携か持ち込みか／写真映像を外注するか | K8: 150 | L8: 400 | M8: 初回見積から100万円以上増える／準備が片方に偏る | N8: 未着手
A9: P6 | B9: 結婚式・新婚旅行 | C9: 式が終わり、内祝いと精算まで完了した状態 | D9: 1 | E9: 21 | F9: =E9+D9-1 | G9: =EDATE('はじめに'!$C$5,E9) | H9: =EDATE('はじめに'!$C$5,F9) | I9: 挙式・披露宴／新婚旅行／お礼と精算 | J9: 新婚旅行の時期（妊活とどちらを先にするか）／渡航先（感染症リスク地域を避ける） | K9: 40 | L9: 120 | M9: 旅行と妊活・妊娠が重なり渡航できない | N9: 未着手
A10: P7 | B10: 妊活の準備 | C10: 2人とも検査を終え、妊娠しやすい体と生活の準備ができた状態 | D10: 4 | E10: 18 | F10: =E10+D10-1 | G10: =EDATE('はじめに'!$C$5,E10) | H10: =EDATE('はじめに'!$C$5,F10) | I10: ブライダルチェック／精液検査／風疹抗体／葉酸開始 | J10: 検査をどこで受けるか／何ヶ月で受診に切り替えるか／不妊治療をどこまでやるか（費用と期限） | K10: 3 | L10: 15 | M10: 男性側が検査を受けず、当事者意識に差が出る | N10: 未着手
A11: P8 | B11: 妊活 | C11: 妊娠が判明している状態 | D11: 6 | E11: 22 | F11: =E11+D11-1 | G11: =EDATE('はじめに'!$C$5,E11) | H11: =EDATE('はじめに'!$C$5,F11) | I11: タイミング法／必要ならクリニック受診・AIH・IVF | J11: クリニックの選定／人工授精・体外受精へ進む条件／治療費の上限と「やめどき」 | K11: 0 | L11: 200 | M11: 義務化した性交渉・費用・やめどきで関係が消耗する | N11: 未着手
A12: P9 | B12: 妊娠初期〜中期 | C12: 母子手帳を取得し、産院と出生前検査の方針が決まっている状態 | D12: 6 | E12: 28 | F12: =E12+D12-1 | G12: =EDATE('はじめに'!$C$5,E12) | H12: =EDATE('はじめに'!$C$5,F12) | I12: 心拍確認／母子手帳／分娩予約／両親学級／保育園見学 | J12: 産院（総合病院／クリニック／助産院・無痛の有無）／出生前検査を受けるか／里帰りするか／保活を見越した引っ越しの要否 | K12: 5 | L12: 25 | M12: 出生前検査の是非で価値観が衝突する | N12: 未着手
A13: P10 | B13: 妊娠後期・出産準備 | C13: 入院バッグ・育児用品・産後の体制が全て整っている状態 | D13: 3 | E13: 34 | F13: =E13+D13-1 | G13: =EDATE('はじめに'!$C$5,E13) | H13: =EDATE('はじめに'!$C$5,F13) | I13: RSVワクチン／入院バッグ／育児用品購入／産休開始／父の育休申出 | J13: ベビーカー・チャイルドシート・抱っこ紐のメーカー／おむつ・ミルクの銘柄／産後の家事外注／父の育休の取り方 | K13: 20 | L13: 50 | M13: 産後の生活設計をせずに出産日を迎える | N13: 未着手
A14: P11 | B14: 出産・産褥期 | C14: 行政手続きが全て終わり、母体が回復に向かっている状態 | D14: 2 | E14: 37 | F14: =E14+D14-1 | G14: =EDATE('はじめに'!$C$5,E14) | H14: =EDATE('はじめに'!$C$5,F14) | I14: 出産／出生届・児童手当・保険証／新生児訪問／2週間健診 | J14: 誰がどの手続きをやるか／義実家の来訪ルール／夜間対応の分担 | K14: 10 | L14: 40 | M14: 産後の身体的ダメージが理解されず、母が休めない | N14: 未着手
A15: P12 | B15: 育児 生後2〜6ヶ月 | C15: 予防接種が予定通り進み、離乳食が始まっている状態 | D15: 4 | E15: 39 | F15: =E15+D15-1 | G15: =EDATE('はじめに'!$C$5,E15) | H15: =EDATE('はじめに'!$C$5,F15) | I15: 1ヶ月健診／予防接種デビュー／3-4ヶ月健診／BCG／離乳食開始 | J15: かかりつけ小児科／離乳食のメーカーと進め方／ハイチェアなどの選定／復職の時期 | K15: 10 | L15: 25 | M15: 睡眠不足による攻撃性と、産後うつの見落とし | N15: 未着手
A16: P13 | B16: 育児 生後6〜12ヶ月 | C16: 保育園が決まり、復職後の生活が回っている状態 | D16: 6 | E16: 43 | F16: =E16+D16-1 | G16: =EDATE('はじめに'!$C$5,E16) | H16: =EDATE('はじめに'!$C$5,F16) | I16: 保育園申込／9-10ヶ月健診／慣らし保育／1歳／復職 | J16: 認可・認可外の併願戦略／育休を延長するか／復職後の家事育児の再分担／教育資金の置き場所 | K16: 10 | L16: 30 | M16: 保活と復職後の負担配分が片方に集中する | N16: 未着手
B17: 合計 | K17: =SUM(K4:K16) | L17: =SUM(L4:L16) | M17: ※ ご祝儀・親からの援助・各種給付金は差し引く前の総額

Sheet ②WBS
A1: ② WBS｜想定される論点まで分解したタスク一覧 | E1: 濃い行＝タスク／薄い行＝その中の実行ステップ。左の＋−で折りたためます
A2: WBS-ID | B2: フェーズ | C2: 中分類 | D2: Lv | E2: タスク／実行ステップ | F2: 完了の定義（これができたら完了） | G2: 論点・決めること | H2: 選択肢・候補 | I2: 判断軸・注意点 | J2: 経過 月 | K2: 目安時期 | L2: 区分 | M2: 担当 | N2: 所要 目安 | O2: 費用目安 | P2: 先行して終わっていること | Q2: 状態 | R2: メモ
A3: P1-01 | B3: P1 | C3: 方針 | D3: 2 | E3: 同棲の目的と期限を合意する | F3: 「いつまでに結婚するか」が日付で書かれ、2人が見られる場所にある | G3: 何のために同棲するのか／いつまでに結論を出すか | H3: お試し期間として／結婚前提で生活費を抑える／すでに結婚が決まっている | I3: 期限を切らない同棲は「なんとなく長期化」しやすい。1〜2年で結論を出す前提にする | J3: 0 | K3: =EDATE('はじめに'!$C$5,J3) | L3: 推奨 | M3: 2人 | N3: 2時間 | Q3: 未着手
A4: P1-01-01 | B4: P1 | C4: 方針 | D4: 3 | E4: 各自が「同棲に期待すること」「不安なこと」を5つずつ書き出して交換する | F4: 10項目ずつのリストが揃っている | J4: 0 | K4: =EDATE('はじめに'!$C$5,J4) | L4: 推奨 | M4: 2人 | N4: 30分 | Q4: 未着手
A5: P1-01-02 | B5: P1 | C5: 方針 | D5: 3 | E5: 結婚の意思の有無と、結論を出す期限を年月で決める | F5: 「◯年◯月までに結論」が明文化されている | J5: 0 | K5: =EDATE('はじめに'!$C$5,J5) | L5: 推奨 | M5: 2人 | N5: 1時間 | P5: 期待と不安の交換 | Q5: 未着手
A6: P1-01-03 | B6: P1 | C6: 方針 | D6: 3 | E6: 決めた内容を1枚にまとめ、共有ドライブに置く | F6: 2人がいつでも見られるURLがある | J6: 0 | K6: =EDATE('はじめに'!$C$5,J6) | L6: 任意 | M6: どちらか | N6: 30分 | Q6: 未着手
A7: P1-02 | B7: P1 | C7: 住まい | D7: 2 | E7: 住むエリアを決める（将来の保活を見越すか判断する） | F7: 候補5エリアの比較表があり、第1候補が決まっている | G7: 今の通勤で選ぶか、子どもができた後まで見越して選ぶか | H7: ①都心の賃貸（狭いが通勤が楽） ②郊外で広め（保育園に入りやすい傾向） ③どちらかの実家の近く（応援が呼べる） | I7: 保活・医療費助成・通勤・実家距離・災害リスクの5軸で点数化して比較する。子どもを持つ予定があるなら、この判断が後の4年間を規定する | J7: 0 | K7: =EDATE('はじめに'!$C$5,J7) | L7: 推奨 | M7: 2人 | N7: 1〜2週間 | P7: 同棲の目的と期限の合意 | Q7: 未着手
A8: P1-02-01 | B8: P1 | C8: 住まい | D8: 3 | E8: 候補エリアを5つ挙げて比較表の枠を作る | F8: 5行×比較項目の空表ができている | J8: 0 | K8: =EDATE('はじめに'!$C$5,J8) | L8: 推奨 | M8: 2人 | N8: 30分 | Q8: 未着手
A9: P1-02-02 | B9: P1 | C9: 住まい | D9: 3 | E9: 各エリアの認可保育園の待機児童数と0歳児の定員を自治体サイトで調べる | F9: エリアごとの数字が比較表に入っている | J9: 0 | K9: =EDATE('はじめに'!$C$5,J9) | L9: 推奨 | M9: どちらか | N9: 2時間 | Q9: 未着手
A10: P1-02-03 | B10: P1 | C10: 住まい | D10: 3 | E10: 直近の認可保育園の内定最低指数（点数）を調べる | F10: 共働きフルタイムで入れる見込みがあるか判断できる | J10: 0 | K10: =EDATE('はじめに'!$C$5,J10) | L10: 推奨 | M10: どちらか | N10: 1時間 | Q10: 未着手
A11: P1-02-04 | B11: P1 | C11: 住まい | D11: 3 | E11: 子ども医療費助成の対象年齢・所得制限・自己負担を比較する | F11: エリアごとに「何歳まで無料か」が表に入っている | J11: 0 | K11: =EDATE('はじめに'!$C$5,J11) | L11: 推奨 | M11: どちらか | N11: 1時間 | Q11: 未着手
A12: P1-02-05 | B12: P1 | C12: 住まい | D12: 3 | E12: 保育料の階層表と自治体独自の減免（第2子無償化など）を比較する | F12: 想定年収での月額保育料が比較できる | J12: 0 | K12: =EDATE('はじめに'!$C$5,J12) | L12: 任意 | M12: どちらか | N12: 1時間 | Q12: 未着手
A13: P1-02-06 | B13: P1 | C13: 住まい | D13: 3 | E13: 2人の通勤時間をドアtoドアで実測する（乗換案内の数字ではなく実際に移動する） | F13: 実測値が表に入っている | J13: 0 | K13: =EDATE('はじめに'!$C$5,J13) | L13: 推奨 | M13: 2人 | N13: 半日 | Q13: 未着手
A14: P1-02-07 | B14: P1 | C14: 住まい | D14: 3 | E14: 実家・義実家までのドアtoドア所要時間を出す | F14: 「何かあったとき何時間で来られるか」が分かる | J14: 0 | K14: =EDATE('はじめに'!$C$5,J14) | L14: 推奨 | M14: 2人 | N14: 30分 | Q14: 未着手
A15: P1-02-08 | B15: P1 | C15: 住まい | D15: 3 | E15: ハザードマップ（洪水・土砂・地震・液状化）を確認する | F15: 候補エリアの災害リスクが把握できている | J15: 0 | K15: =EDATE('はじめに'!$C$5,J15) | L15: 推奨 | M15: どちらか | N15: 30分 | Q15: 未着手
A16: P1-02-09 | B16: P1 | C16: 住まい | D16: 3 | E16: 小児科・夜間休日診療所・病児保育の分布を調べる | F16: 自転車15分圏内に小児科があるか分かる | J16: 0 | K16: =EDATE('はじめに'!$C$5,J16) | L16: 推奨 | M16: どちらか | N16: 1時間 | Q16: 未着手
A17: P1-02-10 | B17: P1 | C17: 住まい | D17: 3 | E17: 家賃相場・更新料の慣習・駐輪場の有無を比較する | F17: 月額の総コストが比較できる | J17: 0 | K17: =EDATE('はじめに'!$C$5,J17) | L17: 推奨 | M17: 2人 | N17: 1時間 | Q17: 未着手
A18: P1-02-11 | B18: P1 | C18: 住まい | D18: 3 | E18: 上位2エリアを平日夜と休日昼にそれぞれ歩く | F18: 夜の明るさ・人通り・買い物のしやすさを体感している | J18: 0 | K18: =EDATE('はじめに'!$C$5,J18) | L18: 推奨 | M18: 2人 | N18: 1日 | Q18: 未着手
A19: P1-02-12 | B19: P1 | C19: 住まい | D19: 3 | E19: 比較表に結論と理由を書いて、エリアを確定する | F19: 第1候補が決まり、理由が書かれている | J19: 1 | K19: =EDATE('はじめに'!$C$5,J19) | L19: 推奨 | M19: 2人 | N19: 1時間 | Q19: 未着手
A20: P1-03 | B20: P1 | C20: 住まい | D20: 2 | E20: 物件の条件を確定する | F20: 不動産会社にそのまま渡せる条件シートがある | G20: 子どもが生まれた後も住み続けられる物件かどうか | H20: 1LDK（同棲のみ・2年で住み替え前提）／2LDK以上（出産後も住める）／分譲賃貸 | I20: ベビーカーが通る玄関幅とエレベーターの有無／階数（ベビーカーを担げるか）／更新料／2年以内に引っ越す前提なら初期費用を抑える | J20: 1 | K20: =EDATE('はじめに'!$C$5,J20) | L20: 推奨 | M20: 2人 | N20: 3時間 | P20: 住むエリアの決定 | Q20: 未着手
A21: P1-03-01 | B21: P1 | C21: 住まい | D21: 3 | E21: 家賃の上限を「2人の手取り合計の◯%」で決める | F21: 上限額が数字で決まっている | J21: 1 | K21: =EDATE('はじめに'!$C$5,J21) | L21: 推奨 | M21: 2人 | N21: 30分 | Q21: 未着手
A22: P1-03-02 | B22: P1 | C22: 住まい | D22: 3 | E22: 間取りの最低条件を決める（在宅勤務のスペース、将来の子ども部屋） | F22: 必要な部屋数と広さが決まっている | J22: 1 | K22: =EDATE('はじめに'!$C$5,J22) | L22: 推奨 | M22: 2人 | N22: 30分 | Q22: 未着手
A23: P1-03-03 | B23: P1 | C23: 住まい | D23: 3 | E23: ベビーカー基準の条件を入れる（玄関幅・エレベーター・段差・オートロック） | F23: 条件シートに物理条件が入っている | J23: 1 | K23: =EDATE('はじめに'!$C$5,J23) | L23: 推奨 | M23: 2人 | N23: 30分 | Q23: 未着手
A24: P1-03-04 | B24: P1 | C24: 住まい | D24: 3 | E24: 各自が「譲れない条件」と「妥協できる条件」を3つずつ出す | F24: 優先順位が可視化されている | J24: 1 | K24: =EDATE('はじめに'!$C$5,J24) | L24: 推奨 | M24: 2人 | N24: 30分 | Q24: 未着手
A25: P1-04 | B25: P1 | C25: 住まい | D25: 2 | E25: 内見・申込・賃貸借契約 | F25: 鍵の引き渡し日が確定している | J25: 1 | K25: =EDATE('はじめに'!$C$5,J25) | L25: 推奨 | M25: 2人 | N25: 2〜3週間 | O25: 40〜80万円 | P25: 物件条件の確定 | Q25: 未着手
A26: P1-04-01 | B26: P1 | C26: 住まい | D26: 3 | E26: 不動産会社を2〜3社に絞って条件シートを渡す | F26: 各社から物件提案が来ている | J26: 1 | K26: =EDATE('はじめに'!$C$5,J26) | L26: 推奨 | M26: どちらか | N26: 2時間 | Q26: 未着手
A27: P1-04-02 | B27: P1 | C27: 住まい | D27: 3 | E27: 内見のチェックリストを作る（携帯の電波・水圧・騒音・コンセント位置・収納・24hゴミ出し・洗濯機置場のサイズ） | F27: チェックリストが手元にある | J27: 1 | K27: =EDATE('はじめに'!$C$5,J27) | L27: 推奨 | M27: どちらか | N27: 30分 | Q27: 未着手
A28: P1-04-03 | B28: P1 | C28: 住まい | D28: 3 | E28: 内見を1日3〜5件まとめて回る | F28: 候補が2〜3件に絞れている | J28: 1 | K28: =EDATE('はじめに'!$C$5,J28) | L28: 推奨 | M28: 2人 | N28: 1日 | Q28: 未着手
A29: P1-04-04 | B29: P1 | C29: 住まい | D29: 3 | E29: 申込・入居審査（保証会社／連帯保証人） | F29: 審査が通っている | J29: 1 | K29: =EDATE('はじめに'!$C$5,J29) | L29: 推奨 | M29: どちらか | N29: 1週間 | Q29: 未着手
A30: P1-04-05 | B30: P1 | C30: 住まい | D30: 3 | E30: 重要事項説明を受け、更新料・原状回復・退去予告期間・二人入居可を確認して契約する | F30: 契約書に署名し、控えを保管している | J30: 2 | K30: =EDATE('はじめに'!$C$5,J30) | L30: 法定 | M30: 2人 | N30: 2時間 | Q30: 未着手
A31: P1-04-06 | B31: P1 | C31: 住まい | D31: 3 | E31: 初期費用を支払い、鍵の受け取り日を確定する | F31: 入居日が決まっている | J31: 2 | K31: =EDATE('はじめに'!$C$5,J31) | L31: 推奨 | M31: どちらか | N31: 30分 | Q31: 未着手
A32: P1-05 | B32: P1 | C32: お金 | D32: 2 | E32: 初期費用の分担ルールを決める | F32: 誰がいくら出すかと、解消時の扱いが書面になっている | G32: 敷金礼金・引越し・家具家電を誰がいくら出すか | H32: 完全折半／収入比例／費目別（家賃は多い方・家電は少ない方） | I32: 解消したときに揉めないよう、高額家具の名義と持ち出しルールまで決めておく | J32: 0 | K32: =EDATE('はじめに'!$C$5,J32) | L32: 推奨 | M32: 2人 | N32: 2時間 | Q32: 未着手
A33: P1-05-01 | B33: P1 | C33: お金 | D33: 3 | E33: 初期費用の総額を見積もる（敷金・礼金・仲介手数料・前家賃・火災保険・鍵交換・引越し・家具家電） | F33: 総額の見積もりが数字で出ている | J33: 0 | K33: =EDATE('はじめに'!$C$5,J33) | L33: 推奨 | M33: 2人 | N33: 1時間 | Q33: 未着手
A34: P1-05-02 | B34: P1 | C34: お金 | D34: 3 | E34: 負担割合を決める（折半／収入比例／費目別） | F34: 各自の負担額が確定している | J34: 0 | K34: =EDATE('はじめに'!$C$5,J34) | L34: 推奨 | M34: 2人 | N34: 30分 | Q34: 未着手
A35: P1-05-03 | B35: P1 | C35: お金 | D35: 3 | E35: 5万円以上の家具家電の名義と、解消時の扱いを決めて書き残す | F35: リストと扱いが書面になっている | J35: 0 | K35: =EDATE('はじめに'!$C$5,J35) | L35: 推奨 | M35: 2人 | N35: 30分 | Q35: 未着手
A36: P1-06 | B36: P1 | C36: お金 | D36: 2 | E36: 生活費の分担方式と共通口座を決める | F36: 共通口座が開設され、自動送金が設定されている | G36: 毎月いくらを共通に入れ、何を共通費とするか | H36: ①完全折半 ②収入比例 ③費目別分担 ④全額共通＋各自にお小遣い | I36: 同棲期の最大の火種。共通費の定義（食費は？外食は？デート代は？帰省費は？）まで書き出す。収入差があるなら折半は不満が出やすい | J36: 2 | K36: =EDATE('はじめに'!$C$5,J36) | L36: 推奨 | M36: 2人 | N36: 1週間 | P36: 初期費用の分担ルール | Q36: 未着手
A37: P1-06-01 | B37: P1 | C37: お金 | D37: 3 | E37: 2人の手取りと固定費を全部書き出して突き合わせる | F37: 毎月の収支が1枚にまとまっている | J37: 2 | K37: =EDATE('はじめに'!$C$5,J37) | L37: 推奨 | M37: 2人 | N37: 2時間 | Q37: 未着手
A38: P1-06-02 | B38: P1 | C38: お金 | D38: 3 | E38: 共通費の定義を項目単位で決める（食費・日用品・外食・デート代・帰省費・家電） | F38: 共通費に入る／入らないの線引きが文章になっている | J38: 2 | K38: =EDATE('はじめに'!$C$5,J38) | L38: 推奨 | M38: 2人 | N38: 1時間 | Q38: 未着手
A39: P1-06-03 | B39: P1 | C39: お金 | D39: 3 | E39: 共通口座を開設する（ネット銀行が管理しやすい） | F39: 口座があり、2人が残高を見られる | J39: 2 | K39: =EDATE('はじめに'!$C$5,J39) | L39: 推奨 | M39: どちらか | N39: 1時間 | Q39: 未着手
A40: P1-06-04 | B40: P1 | C40: お金 | D40: 3 | E40: 毎月の入金額と入金日を決めて自動送金を設定する | F40: 自動送金が動いている | J40: 2 | K40: =EDATE('はじめに'!$C$5,J40) | L40: 推奨 | M40: 2人 | N40: 30分 | Q40: 未着手
A41: P1-06-05 | B41: P1 | C41: お金 | D41: 3 | E41: 共通の決済手段（クレカ／デビット）を作るか決める | F41: 共通費の支払い方法が1つに決まっている | J41: 2 | K41: =EDATE('はじめに'!$C$5,J41) | L41: 任意 | M41: どちらか | N41: 1時間 | Q41: 未着手
A42: P1-06-06 | B42: P1 | C42: お金 | D42: 3 | E42: 家計管理アプリを2人で連携する | F42: 2人が同じ画面を見られる | G42: どのツールを使うか | H42: マネーフォワードME／Zaim／OsidOri（夫婦向け）／スプレッドシート | I42: 見えない支出があると疑心が生まれる。2人で見られることが最優先 | J42: 2 | K42: =EDATE('はじめに'!$C$5,J42) | L42: 推奨 | M42: 2人 | N42: 1時間 | O42: 0〜1,000円/月 | Q42: 未着手
A43: P1-06-07 | B43: P1 | C43: お金 | D43: 3 | E43: 月1回の家計レビュー日をカレンダーに繰り返し登録する | F43: 予定が毎月入っている | J43: 2 | K43: =EDATE('はじめに'!$C$5,J43) | L43: 推奨 | M43: 2人 | N43: 10分 | Q43: 未着手
A44: P1-07 | B44: P1 | C44: 家事 | D44: 2 | E44: 家事を分解して分担を設計する | F44: 50項目前後の家事一覧に担当が割り当てられ、見える場所にある | G44: 名前のない家事まで洗い出せているか | H44: 曜日固定／得意分野で分ける／週替わり／外注する | I44: 「ゴミ出しをする」だけでなく、袋の補充・分別・収集日の把握・ゴミ箱の掃除まで別タスク。40〜60項目に分解すると偏りが見える | J44: 2 | K44: =EDATE('はじめに'!$C$5,J44) | L44: 推奨 | M44: 2人 | N44: 3時間 | Q44: 未着手
A45: P1-07-01 | B45: P1 | C45: 家事 | D45: 3 | E45: 家事を50項目に分解して書き出す（名前のない家事を含む） | F45: 一覧ができている | J45: 2 | K45: =EDATE('はじめに'!$C$5,J45) | L45: 推奨 | M45: 2人 | N45: 1時間 | Q45: 未着手
A46: P1-07-02 | B46: P1 | C46: 家事 | D46: 3 | E46: 各項目に頻度と所要時間を入れて、合計時間を出す | F46: 週あたりの総家事時間が数字で出ている | J46: 2 | K46: =EDATE('はじめに'!$C$5,J46) | L46: 推奨 | M46: 2人 | N46: 1時間 | Q46: 未着手
A47: P1-07-03 | B47: P1 | C47: 家事 | D47: 3 | E47: 担当を割り当て、合計時間が偏っていないか確認する | F47: 各自の週あたり家事時間が近い | J47: 2 | K47: =EDATE('はじめに'!$C$5,J47) | L47: 推奨 | M47: 2人 | N47: 30分 | Q47: 未着手
A48: P1-07-04 | B48: P1 | C48: 家事 | D48: 3 | E48: 外注・家電に任せる項目を決める | F48: 人がやらない項目が決まっている | J48: 2 | K48: =EDATE('はじめに'!$C$5,J48) | L48: 任意 | M48: 2人 | N48: 30分 | Q48: 未着手
A49: P1-07-05 | B49: P1 | C49: 家事 | D49: 3 | E49: 分担表を冷蔵庫か共有アプリに置く | F49: いつでも参照できる | J49: 2 | K49: =EDATE('はじめに'!$C$5,J49) | L49: 推奨 | M49: どちらか | N49: 15分 | Q49: 未着手
A50: P1-08 | B50: P1 | C50: 手続き | D50: 2 | E50: 引越しと住民票まわりの手続きを完了する | F50: 住民票が新住所になり、ライフラインが全て開通している | J50: 2 | K50: =EDATE('はじめに'!$C$5,J50) | L50: 法定 | M50: 2人 | N50: 1〜2週間 | O50: 8〜20万円 | P50: 賃貸借契約 | Q50: 未着手
A51: P1-08-01 | B51: P1 | C51: 手続き | D51: 3 | E51: 引越し日を決める（繁忙期3〜4月は費用2〜3倍） | F51: 日程が確定している | J51: 1 | K51: =EDATE('はじめに'!$C$5,J51) | L51: 推奨 | M51: 2人 | N51: 30分 | Q51: 未着手
A52: P1-08-02 | B52: P1 | C52: 手続き | D52: 3 | E52: 一括見積で引越し業者を3社比較して予約する | F52: 業者が確定している | J52: 1 | K52: =EDATE('はじめに'!$C$5,J52) | L52: 推奨 | M52: どちらか | N52: 2時間 | Q52: 未着手
A53: P1-08-03 | B53: P1 | C53: 手続き | D53: 3 | E53: 不用品の処分（粗大ゴミの予約は2週間前が目安） | F53: 処分が完了している | J53: 1 | K53: =EDATE('はじめに'!$C$5,J53) | L53: 推奨 | M53: 2人 | N53: 1週間 | Q53: 未着手
A54: P1-08-04 | B54: P1 | C54: 手続き | D54: 3 | E54: 電気・ガス・水道の停止と開始（ガスの開栓は立会いが必要） | F54: 全て開通している | J54: 2 | K54: =EDATE('はじめに'!$C$5,J54) | L54: 法定 | M54: 2人 | N54: 1時間 | Q54: 未着手
A55: P1-08-05 | B55: P1 | C55: 手続き | D55: 3 | E55: インターネット回線を申し込む（開通まで2週間〜1ヶ月かかる） | F55: 開通日が決まっている | J55: 1 | K55: =EDATE('はじめに'!$C$5,J55) | L55: 推奨 | M55: どちらか | N55: 1時間 | Q55: 未着手
A56: P1-08-06 | B56: P1 | C56: 手続き | D56: 3 | E56: 郵便物の転送届を出す | F56: 転送が設定されている | J56: 2 | K56: =EDATE('はじめに'!$C$5,J56) | L56: 推奨 | M56: 2人 | N56: 15分 | Q56: 未着手
A57: P1-08-07 | B57: P1 | C57: 手続き | D57: 3 | E57: 転出届（旧住所）を出す | F57: 転出証明書を受け取っている | J57: 2 | K57: =EDATE('はじめに'!$C$5,J57) | L57: 法定 | M57: 2人 | N57: 1時間 | Q57: 未着手
A58: P1-08-08 | B58: P1 | C58: 手続き | D58: 3 | E58: 転入届を出す（引越しから14日以内） | F58: 新住所の住民票が取れる | J58: 2 | K58: =EDATE('はじめに'!$C$5,J58) | L58: 法定 | M58: 2人 | N58: 1時間 | Q58: 未着手
A59: P1-08-09 | B59: P1 | C59: 手続き | D59: 3 | E59: 世帯を同一にするか別世帯にするか決めて届け出る | F59: 世帯構成が決まっている | G59: 同一世帯にするか、世帯分離のままにするか | H59: 同一世帯（世帯主＋同居人）／別世帯のまま | I59: 国民健康保険料や各種助成の判定が世帯単位のことがある。会社の家賃補助の条件にも影響する | J59: 2 | K59: =EDATE('はじめに'!$C$5,J59) | L59: 法定 | M59: 2人 | N59: 30分 | Q59: 未着手
A60: P1-08-10 | B60: P1 | C60: 手続き | D60: 3 | E60: マイナンバーカードの住所変更（転入から90日以内） | F60: カードに新住所が記載されている | J60: 2 | K60: =EDATE('はじめに'!$C$5,J60) | L60: 法定 | M60: 2人 | N60: 30分 | Q60: 未着手
A61: P1-08-11 | B61: P1 | C61: 手続き | D61: 3 | E61: 運転免許証の住所変更 | F61: 免許証が新住所になっている | J61: 2 | K61: =EDATE('はじめに'!$C$5,J61) | L61: 法定 | M61: 2人 | N61: 1時間 | Q61: 未着手
A62: P1-08-12 | B62: P1 | C62: 手続き | D62: 3 | E62: 火災保険・家財保険に加入する（個人賠償責任特約の有無を確認） | F62: 証券が手元にある | J62: 2 | K62: =EDATE('はじめに'!$C$5,J62) | L62: 推奨 | M62: どちらか | N62: 1時間 | O62: 1〜2万円/2年 | Q62: 未着手
A63: P1-09 | B63: P1 | C63: 住まい | D63: 2 | E63: 家具・家電を揃える | F63: 生活が始められる状態になっている | G63: どちらが買うか、時短家電を今入れるか | H63: 新規購入／どちらかの物を持ち込み／レンタル（CLAS、subsclife） | I63: ドラム式洗濯乾燥機と食洗機は産後の最重要投資。ここで入れておくと後が圧倒的に楽。設置工事は納期がかかる | J63: 2 | K63: =EDATE('はじめに'!$C$5,J63) | L63: 推奨 | M63: 2人 | N63: 2週間 | O63: 20〜50万円 | P63: 賃貸借契約 | Q63: 未着手
A64: P1-09-01 | B64: P1 | C64: 住まい | D64: 3 | E64: 持ち寄る物と買う物を仕分ける | F64: 買い物リストができている | J64: 2 | K64: =EDATE('はじめに'!$C$5,J64) | L64: 推奨 | M64: 2人 | N64: 1時間 | Q64: 未着手
A65: P1-09-02 | B65: P1 | C65: 住まい | D65: 3 | E65: 冷蔵庫・洗濯機・ベッドのサイズを搬入経路（玄関・廊下・階段）で確認する | F65: 実測して入ることが確認できている | J65: 2 | K65: =EDATE('はじめに'!$C$5,J65) | L65: 推奨 | M65: 2人 | N65: 1時間 | Q65: 未着手
A66: P1-09-03 | B66: P1 | C66: 住まい | D66: 3 | E66: 時短家電（ドラム式・食洗機・ロボット掃除機）を今入れるか判断する | F66: 入れる／入れないが決まっている | J66: 2 | K66: =EDATE('はじめに'!$C$5,J66) | L66: 任意 | M66: 2人 | N66: 1時間 | O66: 15〜40万円 | Q66: 未着手
A67: P1-09-04 | B67: P1 | C67: 住まい | D67: 3 | E67: 購入と設置工事を予約する（食洗機の分岐水栓工事は要手配） | F67: 設置日が決まっている | J67: 2 | K67: =EDATE('はじめに'!$C$5,J67) | L67: 推奨 | M67: どちらか | N67: 2時間 | Q67: 未着手
A68: P1-10 | B68: P1 | C68: 関係 | D68: 2 | E68: 両家への同棲報告 | F68: 報告の要否が決まり、必要な報告が済んでいる | G68: 報告するか、するならどのタイミングか | H68: 事前に報告／事後報告／結婚が決まってから | I68: 相手の親の価値観による。報告しないことが後で不信につながるケースがある。各自が自分の実親に伝えるのが原則 | J68: 2 | K68: =EDATE('はじめに'!$C$5,J68) | L68: 任意 | M68: 2人 | N68: 1週間 | Q68: 未着手
A69: P1-10-01 | B69: P1 | C69: 関係 | D69: 3 | E69: 各自が自分の実親の反応を予想して共有する | F69: 想定される反応を2人が把握している | J69: 2 | K69: =EDATE('はじめに'!$C$5,J69) | L69: 任意 | M69: 2人 | N69: 30分 | Q69: 未着手
A70: P1-10-02 | B70: P1 | C70: 関係 | D70: 3 | E70: 各自が自分の実親に伝える | F70: 両家に伝わっている | J70: 2 | K70: =EDATE('はじめに'!$C$5,J70) | L70: 任意 | M70: 2人 | N70: 1時間 | Q70: 未着手
A71: P2-01 | B71: P2 | C71: 関係 | D71: 2 | E71: 週1回15分の夫婦ミーティングを習慣化する | F71: 4週連続で実施できている | G71: 何を議題にするか、いつやるか | H71: 日曜夜／土曜朝／平日夜の固定枠 | I71: この習慣があるかどうかが、産後の関係を最も左右する。定例化しないと必ず消える。議題を固定すると続く | J71: 3 | K71: =EDATE('はじめに'!$C$5,J71) | L71: 推奨 | M71: 2人 | N71: 15分/週 | Q71: 未着手
A72: P2-01-01 | B72: P2 | C72: 関係 | D72: 3 | E72: 議題テンプレートを作る（家事・お金・体調・来週の予定・言えていないこと） | F72: 毎回同じ5項目で回せる | J72: 3 | K72: =EDATE('はじめに'!$C$5,J72) | L72: 推奨 | M72: 2人 | N72: 30分 | Q72: 未着手
A73: P2-01-02 | B73: P2 | C73: 関係 | D73: 3 | E73: 曜日と時間を固定してカレンダーに繰り返し登録する | F73: 予定が毎週入っている | J73: 3 | K73: =EDATE('はじめに'!$C$5,J73) | L73: 推奨 | M73: どちらか | N73: 10分 | Q73: 未着手
A74: P2-01-03 | B74: P2 | C74: 関係 | D74: 3 | E74: 4週やってみて、続く形に調整する | F74: 無理なく続く形になっている | J74: 4 | K74: =EDATE('はじめに'!$C$5,J74) | L74: 推奨 | M74: 2人 | N74: 15分 | Q74: 未着手
A75: P2-02 | B75: P2 | C75: 関係 | D75: 2 | E75: 喧嘩のルールを決める | F75: ルールが紙に書かれ、2人が同意している | G75: 揉めたときにどう収めるか | H75: 人格否定をしない／過去を持ち出さない／その日のうちに無理に終わらせない／30分で一旦中断する／第三者を巻き込まない | I75: ルールを平時に決めておくと、有事に機能する。産後の睡眠不足下では特に効く | J75: 4 | K75: =EDATE('はじめに'!$C$5,J75) | L75: 推奨 | M75: 2人 | N75: 1時間 | Q75: 未着手
A76: P2-02-01 | B76: P2 | C76: 関係 | D76: 3 | E76: 各自が「これを言われると終わる」というNGワードを3つ出す | F76: NGワードが共有されている | J76: 4 | K76: =EDATE('はじめに'!$C$5,J76) | L76: 推奨 | M76: 2人 | N76: 30分 | Q76: 未着手
A77: P2-02-02 | B77: P2 | C77: 関係 | D77: 3 | E77: 中断と再開のルールを決める（何分で中断、いつ再開するか） | F77: ルールが決まっている | J77: 4 | K77: =EDATE('はじめに'!$C$5,J77) | L77: 推奨 | M77: 2人 | N77: 30分 | Q77: 未着手
A78: P2-03 | B78: P2 | C78: 家事 | D78: 2 | E78: 家事分担を運用し、月次で見直す | F78: 毎月1回の見直しが3回続いている | J78: 4 | K78: =EDATE('はじめに'!$C$5,J78) | L78: 推奨 | M78: 2人 | N78: 30分/月 | P78: 家事分担の設計 | Q78: 未着手
A79: P2-03-01 | B79: P2 | C79: 家事 | D79: 3 | E79: 1ヶ月運用して、分担表と実態のズレを洗い出す | F79: ズレている項目が特定できている | J79: 4 | K79: =EDATE('はじめに'!$C$5,J79) | L79: 推奨 | M79: 2人 | N79: 30分 | Q79: 未着手
A80: P2-03-02 | B80: P2 | C80: 家事 | D80: 3 | E80: 「やった感」ではなく所要時間で測り直す | F80: 各自の実測時間が出ている | J80: 4 | K80: =EDATE('はじめに'!$C$5,J80) | L80: 推奨 | M80: 2人 | N80: 30分 | Q80: 未着手
A81: P2-03-03 | B81: P2 | C81: 家事 | D81: 3 | E81: 偏っている項目を再配分するか外注に回す | F81: 分担表が更新されている | J81: 5 | K81: =EDATE('はじめに'!$C$5,J81) | L81: 推奨 | M81: 2人 | N81: 30分 | Q81: 未着手
A82: P2-04 | B82: P2 | C82: お金 | D82: 2 | E82: 貯蓄目標を3本立てで設定する | F82: 3つの目標額と毎月の積立額が決まっている | G82: 何にいくら必要かを分けて積む | H82: ①結婚式資金 ②出産・育児資金 ③住宅／生活防衛資金 | I82: 式150〜400万円、出産〜1歳で50〜100万円（給付金差引後）、生活防衛資金は生活費6ヶ月分が目安 | J82: 4 | K82: =EDATE('はじめに'!$C$5,J82) | L82: 推奨 | M82: 2人 | N82: 2時間 | P82: 共通口座の運用開始 | Q82: 未着手
A83: P2-04-01 | B83: P2 | C83: お金 | D83: 3 | E83: 3つの目的別に必要額と時期を書き出す | F83: 目標額と期日が数字で出ている | J83: 4 | K83: =EDATE('はじめに'!$C$5,J83) | L83: 推奨 | M83: 2人 | N83: 1時間 | Q83: 未着手
A84: P2-04-02 | B84: P2 | C84: お金 | D84: 3 | E84: 目的別に口座または費目を分ける | F84: どこにいくら貯まっているか一目で分かる | J84: 4 | K84: =EDATE('はじめに'!$C$5,J84) | L84: 推奨 | M84: どちらか | N84: 1時間 | Q84: 未着手
A85: P2-04-03 | B85: P2 | C85: お金 | D85: 3 | E85: 毎月の積立を自動化する | F85: 自動積立が動いている | J85: 4 | K85: =EDATE('はじめに'!$C$5,J85) | L85: 推奨 | M85: 2人 | N85: 30分 | Q85: 未着手
A86: P2-05 | B86: P2 | C86: お金 | D86: 2 | E86: 各自が自由に使える額を確定する | F86: 各自の自由費の上限が数字で決まっている | G86: 共通費と貯蓄を引いた後、いくらを個人裁量にするか | H86: 定額お小遣い制／手取りの◯%／上限だけ決めて中身は問わない | I86: ここを曖昧にすると必ず揉める。相手の趣味への課金額に口を出さない代わりに、上限だけ決めるのが運用しやすい | J86: 5 | K86: =EDATE('はじめに'!$C$5,J86) | L86: 推奨 | M86: 2人 | N86: 1時間 | P86: 貯蓄目標の設定 | Q86: 未着手
A87: P2-06 | B87: P2 | C87: お金 | D87: 2 | E87: 保険を棚卸しして見直す | F87: 2人の契約内容が一覧になり、不足と過剰が判断できている | G87: 独身時代の契約のままになっていないか | H87: 職場の団体保険／共済／民間の医療・生命・就業不能 | I87: 女性の医療保険は妊娠前の加入が原則。妊娠後は子宮関連が不担保になりやすいので、P7より前に済ませる | J87: 6 | K87: =EDATE('はじめに'!$C$5,J87) | L87: 推奨 | M87: 2人 | N87: 3時間 | Q87: 未着手
A88: P2-06-01 | B88: P2 | C88: お金 | D88: 3 | E88: 現在加入している全ての保険を一覧にする（保障内容・保険料・受取人） | F88: 一覧表ができている | J88: 6 | K88: =EDATE('はじめに'!$C$5,J88) | L88: 推奨 | M88: 2人 | N88: 1時間 | Q88: 未着手
A89: P2-06-02 | B89: P2 | C89: お金 | D89: 3 | E89: 勤務先の団体保険・共済の内容を確認する | F89: 会社経由で入れる保障が分かっている | J89: 6 | K89: =EDATE('はじめに'!$C$5,J89) | L89: 推奨 | M89: 2人 | N89: 1時間 | Q89: 未着手
A90: P2-06-03 | B90: P2 | C90: お金 | D90: 3 | E90: 医療保険（帝王切開・切迫早産に備える）を妊娠前に整える | F90: 必要な保障に入っている | J90: 6 | K90: =EDATE('はじめに'!$C$5,J90) | L90: 推奨 | M90: 妊娠する側 | N90: 2時間 | Q90: 未着手
A91: P2-06-04 | B91: P2 | C91: お金 | D91: 3 | E91: 不要な保険を解約する | F91: 重複や過剰な契約がなくなっている | J91: 6 | K91: =EDATE('はじめに'!$C$5,J91) | L91: 任意 | M91: 2人 | N91: 1時間 | Q91: 未着手
A92: P2-07 | B92: P2 | C92: お金 | D92: 2 | E92: 資産形成の方針を合わせる | F92: どちらの名義でいくら積むかが決まっている | G92: 教育資金をどこに置くか | H92: 新NISA（つみたて投資枠）／定期預金／学資保険は出産後に検討 | I92: 教育資金は最終的にここか学資保険になる。方針を今のうちに合わせておくと後で揉めない | J92: 6 | K92: =EDATE('はじめに'!$C$5,J92) | L92: 任意 | M92: 2人 | N92: 2時間 | P92: 貯蓄目標の設定 | Q92: 未着手
A93: P2-08 | B93: P2 | C93: 関係 | D93: 2 | E93: お互いの親との距離感を確認する | F93: 訪問頻度・宿泊・連絡の取り方のルールが決まっている | G93: どこまで関わるか、誰が窓口になるか | H93: 月1回訪問／年数回／宿泊あり・なし／連絡は各自が自分の親と | I93: 義実家対応は「各自が自分の実親に言う」が原則。ここを決めておくと産後の衝突が激減する | J93: 7 | K93: =EDATE('はじめに'!$C$5,J93) | L93: 推奨 | M93: 2人 | N93: 2時間 | Q93: 未着手
A94: P2-08-01 | B94: P2 | C94: 関係 | D94: 3 | E94: 各自が自分の実家との理想的な距離感を言葉にする | F94: お互いの希望が分かっている | J94: 7 | K94: =EDATE('はじめに'!$C$5,J94) | L94: 推奨 | M94: 2人 | N94: 30分 | Q94: 未着手
A95: P2-08-02 | B95: P2 | C95: 関係 | D95: 3 | E95: 訪問・宿泊・連絡のルールを決める | F95: ルールが明文化されている | J95: 7 | K95: =EDATE('はじめに'!$C$5,J95) | L95: 推奨 | M95: 2人 | N95: 1時間 | Q95: 未着手
A96: P2-08-03 | B96: P2 | C96: 関係 | D96: 3 | E96: 「相手の親への要望は、自分の親に自分で言う」を原則として合意する | F96: 原則が共有されている | J96: 7 | K96: =EDATE('はじめに'!$C$5,J96) | L96: 推奨 | M96: 2人 | N96: 15分 | Q96: 未着手
A97: P2-09 | B97: P2 | C97: キャリア | D97: 2 | E97: 今後3年の働き方・キャリアの予定を共有する | F97: 2人の3年計画が1枚にまとまっている | G97: 転職・異動・留学・独立の予定が妊活や出産と衝突しないか | I97: 妊活・出産の時期と、キャリアの山場が重なると詰む。先に並べて可視化する | J97: 8 | K97: =EDATE('はじめに'!$C$5,J97) | L97: 推奨 | M97: 2人 | N97: 2時間 | Q97: 未着手
A98: P2-09-01 | B98: P2 | C98: キャリア | D98: 3 | E98: 各自が3年以内にやりたいこと（転職・昇進・資格・留学）を書き出す | F98: リストが揃っている | J98: 8 | K98: =EDATE('はじめに'!$C$5,J98) | L98: 推奨 | M98: 2人 | N98: 30分 | Q98: 未着手
A99: P2-09-02 | B99: P2 | C99: キャリア | D99: 3 | E99: ①ロードマップの時期と並べて、衝突する箇所を洗い出す | F99: 衝突ポイントが特定できている | J99: 8 | K99: =EDATE('はじめに'!$C$5,J99) | L99: 推奨 | M99: 2人 | N99: 1時間 | Q99: 未着手
A100: P2-09-03 | B100: P2 | C100: キャリア | D100: 3 | E100: 衝突する場合はどちらを優先するか決める | F100: 優先順位が決まっている | J100: 8 | K100: =EDATE('はじめに'!$C$5,J100) | L100: 推奨 | M100: 2人 | N100: 1時間 | Q100: 未着手
...

Sheet ③リスク管理表
A1: ③ リスク管理表｜各フェーズで配偶者との関係が悪化する想定リスクと対策 | F1: 確率×影響でスコアと優先度が自動計算されます
A2: リスクID | B2: フェーズ | C2: 分類 | D2: リスク事象 | E2: 典型的な場面 | F2: 早期サイン（黄信号） | G2: 相手側から見えている景色 | H2: 確率 (1-5) | I2: 影響 (1-5) | J2: スコア | K2: 優先度 | L2: 予防策（起きる前にやること） | M2: 発生時の初動（24時間以内） | N2: 再発防止（構造の変更） | O2: オーナー | P2: 見直し | Q2: 状態
A3: R001 | B3: P1 | C3: 家事 | D3: 家事分担の不公平感が言語化されないまま蓄積する | E3: 片方が「気づいた方がやる」方式で回している | F3: ため息が増える／「私ばっかり」が出る／黙って先にやってしまう | G3: やっている側：見えない仕事が全部自分に乗っている。やっていない側：頼まれれば やるのに言われない | H3: 4 | I3: 3 | J3: =H3*I3 | K3: =IF(J3>=16,"最優先",IF(J3>=12,"高",IF(J3>=6,"中","低"))) | L3: 家事を50項目に分解して所要時間を入れ、合計が偏っていないか数字で確認する。名前のない家事（日用品の在庫管理、献立を考える、ゴミ袋の補充）を必ず入れる | M3: その場で分担表を開き、偏っている項目を移す。「ありがとう」ではなく担当そのものを動かす | N3: 月1回の棚卸しを定例化する。指示待ちが起きる項目は領域ごとオーナーを渡す | O3: 2人 | P3: 月1回 | Q3: 未着手
A4: R002 | B4: P1 | C4: お金 | D4: 金銭感覚の差が不信につながる | E4: 片方の趣味・交際費への支出が見えない | F4: 支出の話題を避ける／隠れて買う／レシートを捨てる | G4: 使う側：自分の稼ぎから出しているのに責められる。見ている側：将来の貯蓄が崩れるのが怖い | H4: 3 | I4: 4 | J4: =H4*I4 | K4: =IF(J4>=16,"最優先",IF(J4>=12,"高",IF(J4>=6,"中","低"))) | L4: 共通口座＋各自の自由費（金額を明示）の二層構造にする。自由費の中身には口を出さないと明文化する | M4: 責める前に構造を疑う。自由費の額が実態と合っていない可能性が高いので、金額の見直しから入る | N4: 収入が変わるたびに自由費の額を再設定する | O4: 2人 | P4: 月1回 | Q4: 未着手
A5: R003 | B5: P1 | C5: 生活 | D5: 清潔基準・生活リズムの差で摩耗する | E5: 在宅勤務、夜型と朝型、片付けの許容ライン | F5: 無言で片付ける／相手の物を勝手に動かす／舌打ち | G5: 基準が高い側：常に自分が我慢している。低い側：勝手に決められた基準を押し付けられている | H5: 4 | I5: 2 | J5: =H5*I5 | K5: =IF(J5>=16,"最優先",IF(J5>=12,"高",IF(J5>=6,"中","低"))) | L5: 共有スペースの基準だけを2人で決め、写真で残す。個人スペースは干渉しないと合意する | M5: 基準を再交渉する。相手を変えようとせず、掃除の外注か物理的なゾーニングで解決する | N5: 基準を守れない項目は人ではなく仕組み（ロボット掃除機・収納の追加）に寄せる | O5: 2人 | P5: 月1回 | Q5: 未着手
A6: R004 | B6: P1 | C6: 住まい | D6: エリア選定を今の通勤だけで決め、出産後に住み替えが必要になる | E6: 駅近・職場の近さだけで物件を決めた | F6: 保育園の待機児童数を調べていない／2LDKへの住み替えの話が出ていない | G6: 決めた側：今の生活を最適化しただけ。もう一方：将来の話をしてくれない | H6: 3 | I6: 4 | J6: =H6*I6 | K6: =IF(J6>=16,"最優先",IF(J6>=12,"高",IF(J6>=6,"中","低"))) | L6: 契約前に、その自治体の待機児童数・内定最低指数・子ども医療費助成・保育料減免を1時間だけ調べる。子どもを持つ予定なら更新2年で見直す前提にしておく | M6: 妊娠中期までに引っ越す（それ以降は現実的に不可能）。認可の申込前に住民票を移す | N6: 契約更新のたびに「このまま子育てできるか」を議題にする | O6: 2人 | P6: 月1回 | Q6: 未着手
A7: R005 | B7: P1 | C7: 住まい | D7: 初期費用・家具の負担が偏り、解消時に揉める | E7: 片方が家電を全部買った／名義があいまい | F7: 「これは自分が買った」が会話に出る | G7: 多く出した側：損をしている。少ない側：金額でしか評価されていない | H7: 2 | I7: 3 | J7: =H7*I7 | K7: =IF(J7>=16,"最優先",IF(J7>=12,"高",IF(J7>=6,"中","低"))) | L7: 5万円以上の物は名義と解消時の扱いを書面に残す | M7: リストに戻って確認する。感情ではなく取り決めで処理する | N7: 高額な物は共通口座から買う運用に変える | O7: 2人 | P7: 月1回 | Q7: 未着手
A8: R006 | B8: P1 | C8: コミュニケーション | D8: 「言わなくても分かるはず」の期待値ギャップ | E8: 察してほしい側と、言われないと分からない側 | F8: 不機嫌な沈黙が増える／「なんで分からないの」が出る | G8: 察してほしい側：大事にされていない。言われたい側：突然怒られる理由が分からない | H8: 4 | I8: 3 | J8: =H8*I8 | K8: =IF(J8>=16,"最優先",IF(J8>=12,"高",IF(J8>=6,"中","低"))) | L8: 「察するのを期待しない、言葉で言う」を2人のルールとして明文化する。週次ミーティングで言えていないことを話す枠を作る | M8: その場で「何をしてほしかったのか」を具体的な行動レベルで言語化してもらう | N8: 定例の場で不満を溜めない仕組みにする | O8: 2人 | P8: 月1回 | Q8: 未着手
A9: R007 | B9: P1 | C9: 親族 | D9: 相手の親との距離感が合わない | E9: 頻繁に連絡が来る／逆に全く関わらない | F9: 実家の話題を避ける／連絡を無視する | G9: 近い側：家族なんだから当たり前。遠い側：自分の家庭に踏み込まれている | H9: 3 | I9: 3 | J9: =H9*I9 | K9: =IF(J9>=16,"最優先",IF(J9>=12,"高",IF(J9>=6,"中","低"))) | L9: 訪問頻度・宿泊・連絡手段のルールを先に決める。義実家への要望は各自が自分の実親に伝える | M9: 自分の実親に自分で伝える。相手に矢面に立たせない | N9: 年に1回、距離感のルールを見直す | O9: 2人 | P9: 月1回 | Q9: 未着手
A10: R008 | B10: P1 | C10: 方針 | D10: 同棲が長期化し、結婚の話が進まない | E10: 生活が快適で、現状維持のコストが低い | F10: 結婚の話題が出なくなる／片方だけが焦っている | G10: 急がない側：今が幸せなのに何が不満なのか。焦る側：年齢と妊娠の可能性が削られていく | H10: 3 | I10: 4 | J10: =H10*I10 | K10: =IF(J10>=16,"最優先",IF(J10>=12,"高",IF(J10>=6,"中","低"))) | L10: 同棲開始時に「◯年◯月までに結論を出す」と期限を切り、カレンダーに入れておく | M10: 期限が来たら必ず話す。曖昧なまま延長しない。年齢と妊娠率の関係を数字で共有する | N10: 半年ごとに進捗を確認する議題を入れる | O10: 2人 | P10: 月1回 | Q10: 未着手
A11: R009 | B11: P1 | C11: 時間 | D11: 引越し直後の疲労で最初の大喧嘩が起きる | E11: 荷解きが終わらない、想定外の出費、片方だけが動いている | F11: 引越し後1〜2週間で衝突する | G11: 動いている側：自分ばかり。動けていない側：仕事が忙しいのに責められる | H11: 3 | I11: 2 | J11: =H11*I11 | K11: =IF(J11>=16,"最優先",IF(J11>=12,"高",IF(J11>=6,"中","低"))) | L11: 引越し後2週間は予定を入れず、荷解きの担当エリアを分けておく。外食・宅配を前提に食事を組む | M11: 疲労が原因だと認識して、その日は決着させずに寝る | N11: 大きなイベントの直後は判断も喧嘩も先送りするルールにする | O11: 2人 | P11: 月1回 | Q11: 未着手
A12: R010 | B12: P1 | C12: お金 | D12: 共通費の定義が曖昧で、毎月の精算で揉める | E12: 外食・デート代・帰省費が共通か個人かで解釈が違う | F12: 精算のたびに気まずくなる／どちらかが黙って多く払う | G12: 払う側：不公平。もう一方：細かく言われるのが窮屈 | H12: 4 | I12: 2 | J12: =H12*I12 | K12: =IF(J12>=16,"最優先",IF(J12>=12,"高",IF(J12>=6,"中","低"))) | L12: 共通費に入る／入らないを項目単位で文章化する。グレーな項目（外食・デート・帰省）を必ず明記する | M12: 定義に立ち返り、決めていなかった項目をその場で追加する | N12: 毎月のレビューで、揉めた項目を定義に追記していく | O12: 2人 | P12: 月1回 | Q12: 未着手
A13: R011 | B13: P2 | C13: コミュニケーション | D13: 会話が業務連絡だけになる | E13: 生活が回り始め、話すことが減る | F13: ありがとうを言わなくなる／別々に過ごす時間が増える | G13: どちらも：相手が自分に興味を失ったように見える | H13: 4 | I13: 3 | J13: =H13*I13 | K13: =IF(J13>=16,"最優先",IF(J13>=12,"高",IF(J13>=6,"中","低"))) | L13: 週1回15分のミーティングを定例化し、「子ども・家事・お金以外の話」を1つ入れる | M13: 外で2人だけの時間を作る。1〜2時間でも効果がある | N13: 定例を止めない。忙しい時期ほど短くても続ける | O13: 2人 | P13: 月1回 | Q13: 未着手
A14: R012 | B14: P2 | C14: お金 | D14: 貯蓄が計画どおりに進まない | E14: 支出の見積もりが甘い／収入変動 | F14: 3ヶ月連続で目標額に届かない | G14: 貯めたい側：将来が不安。使いたい側：今を楽しめない | H14: 3 | I14: 3 | J14: =H14*I14 | K14: =IF(J14>=16,"最優先",IF(J14>=12,"高",IF(J14>=6,"中","低"))) | L14: 目的別に口座を分けて自動積立にする。手動での貯蓄は続かない | M14: 目標額か期日のどちらかを現実に合わせて下方修正する。放置しない | N14: 収入が変わったら積立額を機械的に再計算する | O14: 2人 | P14: 月1回 | Q14: 未着手
... A133: R131 | B133: 通期 | C133: 意思決定 | D133: 「話し合ったことを忘れる／解釈が違う」 | E133: 口頭で決めたことが記憶違いになる | F133: 「そんなこと言ってない」が出る | G133: どちらも：自分の記憶が正しいと思っている | H133: 4 | I133: 3 | J133: =H133*I133 | K133: =IF(J133>=16,"最優先",IF(J133>=12,"高",IF(J133>=6,"中","低"))) | L133: 決めたことは短くてよいので文字で残す（共有ドライブ・このスプレッドシート） | M133: 記録を見に行く。記録がなければ決めていないものとして決め直す | N133: 重要な合意はこのシートのメモ欄に日付付きで書く | O133: 2人 | P133: 月1回 | Q133: 未着手
